Metadata-Version: 2.1
Name: dnsmeapi
Version: 0.0.2
Summary: make simple dnsmadeeasy api calls
Home-page: https://github.com/engineering-bjs/dnsmeapi
Author: BJS Engineering Team
Author-email: anish@bjshomedelivery.com
License: MIT
Download-URL: https://github.com/engineering-bjs/dnsmeapi/blob/master/archive/dnsmeapi-0.0.1.tar.gz
Keywords: dnsmadeeasy,sha1,python3,requests,hmac
Platform: UNKNOWN
Classifier: Programming Language :: Python :: 3
Classifier: License :: OSI Approved :: MIT License
Classifier: Operating System :: OS Independent
Requires-Python: >=3.7
